{
  "experiment": "agnews",
  "timestamp": "2025-12-14T00:21:43.435607",
  "config": {
    "output_dir": "runs/paper_experiments_20251213_190318/bridge_multiseed/agnews_seed123",
    "steps": 2000,
    "soft_tokens": 8,
    "batch_size": 16,
    "lr": 0.0002,
    "eval_every": 200,
    "diversity_weight": 0.1,
    "source_layer": 31
  },
  "num_classes": 4,
  "final_results": {
    "accuracy": 90.0,
    "correct": 180,
    "total": 200
  },
  "training_log": [
    {
      "step": 200,
      "accuracy": 37.0,
      "correct": 37,
      "total": 100
    },
    {
      "step": 400,
      "accuracy": 89.0,
      "correct": 89,
      "total": 100
    },
    {
      "step": 600,
      "accuracy": 81.0,
      "correct": 81,
      "total": 100
    },
    {
      "step": 800,
      "accuracy": 86.0,
      "correct": 86,
      "total": 100
    },
    {
      "step": 1000,
      "accuracy": 87.0,
      "correct": 87,
      "total": 100
    },
    {
      "step": 1200,
      "accuracy": 87.0,
      "correct": 87,
      "total": 100
    },
    {
      "step": 1400,
      "accuracy": 83.0,
      "correct": 83,
      "total": 100
    },
    {
      "step": 1600,
      "accuracy": 91.0,
      "correct": 91,
      "total": 100
    },
    {
      "step": 1800,
      "accuracy": 93.0,
      "correct": 93,
      "total": 100
    },
    {
      "step": 2000,
      "accuracy": 86.0,
      "correct": 86,
      "total": 100
    }
  ]
}