{
  "functional_pass_gate": true,
  "gate": "source_private_product_codebook_packet_gate",
  "headline": {
    "budgets": [
      2,
      4,
      6
    ],
    "functional_pass_rows": 8,
    "functional_remaps_with_pass": [
      101,
      103,
      107
    ],
    "max_passing_decode_latency_ms": null,
    "max_product_codebook_accuracy": 0.59765625,
    "min_passing_product_codebook_minus_control": null,
    "min_passing_product_codebook_minus_scalar": null,
    "pass_rows": 0,
    "remap_seeds": [
      101,
      103,
      107
    ],
    "remaps_with_pass": [],
    "rows": 9,
    "systems_pass_rows": 0,
    "systems_remaps_with_pass": []
  },
  "interpretation": "This gate tests whether a product-quantized discrete packet can become a compression-native replacement for scalar Wyner-Ziv: each byte is a learned centroid index for one subspace of the source-projected vector. It is a method contribution only if the code indices preserve source-private candidate margins without being explained by label-shuffled, constrained-shuffled, answer-masked, permuted-code, or random controls. The aggregate reports functional pass separately from systems-latency pass because the current implementation uses a simple Python decoder rather than an optimized table-lookup kernel.",
  "pass_gate": false,
  "pass_rule": "At least one product-codebook packet row per remapped codebook must pass source-destroying controls, beat its strongest product-codebook control by >=0.15, stay within 0.02 accuracy of scalar Wyner-Ziv, keep p50 CPU decode latency under 2 ms, and beat query-aware text at the same byte budget.",
  "rows": [
    {
      "best_no_source_accuracy": 0.2578125,
      "best_product_codebook_control_accuracy": 0.25390625,
      "budget_bytes": 2,
      "exact_id_parity": true,
      "mean_payload_bytes": 2.0,
      "mean_payload_tokens": 1.0,
      "n": 256,
      "p50_decode_latency_ms": 10.28518749808427,
      "p95_decode_latency_ms": 44.03645801357925,
      "packet_vs_query_aware_oracle_compression": 7.0,
      "product_codebook_accuracy": 0.57421875,
      "product_codebook_controls_ok": true,
      "product_codebook_minus_best_control": 0.3203125,
      "product_codebook_minus_best_no_source": 0.31640625,
      "product_codebook_minus_protected": 0.16796875,
      "product_codebook_minus_qjl": 0.140625,
      "product_codebook_minus_scalar": 0.125,
      "product_codebook_pass": true,
      "product_codebook_within_002_of_scalar": true,
      "protected_rotated_residual_accuracy": 0.40625,
      "qjl_residual_accuracy": 0.43359375,
      "query_aware_text_at_budget_accuracy": 0.25,
      "remap_slot_seed": 101,
      "result_dir": "/Users/sujeethjinesh/Desktop/LatentWire/results/source_private_product_codebook_packet_gate_20260430/remap_101",
      "rotation_sign_accuracy": 0.296875,
      "scalar_wyner_ziv_accuracy": 0.44921875,
      "target_accuracy": 0.25
    },
    {
      "best_no_source_accuracy": 0.26171875,
      "best_product_codebook_control_accuracy": 0.28125,
      "budget_bytes": 4,
      "exact_id_parity": true,
      "mean_payload_bytes": 4.0,
      "mean_payload_tokens": 1.0,
      "n": 256,
      "p50_decode_latency_ms": 9.658979513915256,
      "p95_decode_latency_ms": 34.608084009960294,
      "packet_vs_query_aware_oracle_compression": 3.5,
      "product_codebook_accuracy": 0.58203125,
      "product_codebook_controls_ok": true,
      "product_codebook_minus_best_control": 0.30078125,
      "product_codebook_minus_best_no_source": 0.3203125,
      "product_codebook_minus_protected": 0.11328125,
      "product_codebook_minus_qjl": 0.05859375,
      "product_codebook_minus_scalar": 0.05078125,
      "product_codebook_pass": true,
      "product_codebook_within_002_of_scalar": true,
      "protected_rotated_residual_accuracy": 0.46875,
      "qjl_residual_accuracy": 0.5234375,
      "query_aware_text_at_budget_accuracy": 0.25,
      "remap_slot_seed": 101,
      "result_dir": "/Users/sujeethjinesh/Desktop/LatentWire/results/source_private_product_codebook_packet_gate_20260430/remap_101",
      "rotation_sign_accuracy": 0.3359375,
      "scalar_wyner_ziv_accuracy": 0.53125,
      "target_accuracy": 0.25
    },
    {
      "best_no_source_accuracy": 0.27734375,
      "best_product_codebook_control_accuracy": 0.29296875,
      "budget_bytes": 6,
      "exact_id_parity": true,
      "mean_payload_bytes": 6.0,
      "mean_payload_tokens": 1.0,
      "n": 256,
      "p50_decode_latency_ms": 9.943979006493464,
      "p95_decode_latency_ms": 42.83241700613871,
      "packet_vs_query_aware_oracle_compression": 2.3333333333333335,
      "product_codebook_accuracy": 0.59765625,
      "product_codebook_controls_ok": true,
      "product_codebook_minus_best_control": 0.3046875,
      "product_codebook_minus_best_no_source": 0.3203125,
      "product_codebook_minus_protected": 0.09375,
      "product_codebook_minus_qjl": 0.05078125,
      "product_codebook_minus_scalar": 0.02734375,
      "product_codebook_pass": true,
      "product_codebook_within_002_of_scalar": true,
      "protected_rotated_residual_accuracy": 0.50390625,
      "qjl_residual_accuracy": 0.546875,
      "query_aware_text_at_budget_accuracy": 0.25,
      "remap_slot_seed": 101,
      "result_dir": "/Users/sujeethjinesh/Desktop/LatentWire/results/source_private_product_codebook_packet_gate_20260430/remap_101",
      "rotation_sign_accuracy": 0.33984375,
      "scalar_wyner_ziv_accuracy": 0.5703125,
      "target_accuracy": 0.25
    },
    {
      "best_no_source_accuracy": 0.26953125,
      "best_product_codebook_control_accuracy": 0.28515625,
      "budget_bytes": 2,
      "exact_id_parity": true,
      "mean_payload_bytes": 2.0,
      "mean_payload_tokens": 1.0,
      "n": 256,
      "p50_decode_latency_ms": 9.039416487212293,
      "p95_decode_latency_ms": 50.45120799331926,
      "packet_vs_query_aware_oracle_compression": 7.0,
      "product_codebook_accuracy": 0.5390625,
      "product_codebook_controls_ok": true,
      "product_codebook_minus_best_control": 0.25390625,
      "product_codebook_minus_best_no_source": 0.26953125,
      "product_codebook_minus_protected": 0.078125,
      "product_codebook_minus_qjl": 0.109375,
      "product_codebook_minus_scalar": 0.0703125,
      "product_codebook_pass": true,
      "product_codebook_within_002_of_scalar": true,
      "protected_rotated_residual_accuracy": 0.4609375,
      "qjl_residual_accuracy": 0.4296875,
      "query_aware_text_at_budget_accuracy": 0.25,
      "remap_slot_seed": 103,
      "result_dir": "/Users/sujeethjinesh/Desktop/LatentWire/results/source_private_product_codebook_packet_gate_20260430/remap_103",
      "rotation_sign_accuracy": 0.3125,
      "scalar_wyner_ziv_accuracy": 0.46875,
      "target_accuracy": 0.25
    },
    {
      "best_no_source_accuracy": 0.2734375,
      "best_product_codebook_control_accuracy": 0.29296875,
      "budget_bytes": 4,
      "exact_id_parity": true,
      "mean_payload_bytes": 4.0,
      "mean_payload_tokens": 1.0,
      "n": 256,
      "p50_decode_latency_ms": 9.41541651263833,
      "p95_decode_latency_ms": 31.22545898077078,
      "packet_vs_query_aware_oracle_compression": 3.5,
      "product_codebook_accuracy": 0.53125,
      "product_codebook_controls_ok": true,
      "product_codebook_minus_best_control": 0.23828125,
      "product_codebook_minus_best_no_source": 0.2578125,
      "product_codebook_minus_protected": 0.05859375,
      "product_codebook_minus_qjl": -0.00390625,
      "product_codebook_minus_scalar": 0.03125,
      "product_codebook_pass": true,
      "product_codebook_within_002_of_scalar": true,
      "protected_rotated_residual_accuracy": 0.47265625,
      "qjl_residual_accuracy": 0.53515625,
      "query_aware_text_at_budget_accuracy": 0.25,
      "remap_slot_seed": 103,
      "result_dir": "/Users/sujeethjinesh/Desktop/LatentWire/results/source_private_product_codebook_packet_gate_20260430/remap_103",
      "rotation_sign_accuracy": 0.34765625,
      "scalar_wyner_ziv_accuracy": 0.5,
      "target_accuracy": 0.25
    },
    {
      "best_no_source_accuracy": 0.26171875,
      "best_product_codebook_control_accuracy": 0.2734375,
      "budget_bytes": 6,
      "exact_id_parity": true,
      "mean_payload_bytes": 6.0,
      "mean_payload_tokens": 1.0,
      "n": 256,
      "p50_decode_latency_ms": 9.498895495198667,
      "p95_decode_latency_ms": 37.79466700507328,
      "packet_vs_query_aware_oracle_compression": 2.3333333333333335,
      "product_codebook_accuracy": 0.55078125,
      "product_codebook_controls_ok": true,
      "product_codebook_minus_best_control": 0.27734375,
      "product_codebook_minus_best_no_source": 0.2890625,
      "product_codebook_minus_protected": 0.015625,
      "product_codebook_minus_qjl": 0.01953125,
      "product_codebook_minus_scalar": 0.01171875,
      "product_codebook_pass": true,
      "product_codebook_within_002_of_scalar": true,
      "protected_rotated_residual_accuracy": 0.53515625,
      "qjl_residual_accuracy": 0.53125,
      "query_aware_text_at_budget_accuracy": 0.25,
      "remap_slot_seed": 103,
      "result_dir": "/Users/sujeethjinesh/Desktop/LatentWire/results/source_private_product_codebook_packet_gate_20260430/remap_103",
      "rotation_sign_accuracy": 0.33203125,
      "scalar_wyner_ziv_accuracy": 0.5390625,
      "target_accuracy": 0.25
    },
    {
      "best_no_source_accuracy": 0.2578125,
      "best_product_codebook_control_accuracy": 0.3125,
      "budget_bytes": 2,
      "exact_id_parity": true,
      "mean_payload_bytes": 2.0,
      "mean_payload_tokens": 1.0,
      "n": 256,
      "p50_decode_latency_ms": 8.31254200602416,
      "p95_decode_latency_ms": 32.90724998805672,
      "packet_vs_query_aware_oracle_compression": 7.0,
      "product_codebook_accuracy": 0.51171875,
      "product_codebook_controls_ok": false,
      "product_codebook_minus_best_control": 0.19921875,
      "product_codebook_minus_best_no_source": 0.25390625,
      "product_codebook_minus_protected": 0.02734375,
      "product_codebook_minus_qjl": 0.0625,
      "product_codebook_minus_scalar": 0.0625,
      "product_codebook_pass": false,
      "product_codebook_within_002_of_scalar": true,
      "protected_rotated_residual_accuracy": 0.484375,
      "qjl_residual_accuracy": 0.44921875,
      "query_aware_text_at_budget_accuracy": 0.25,
      "remap_slot_seed": 107,
      "result_dir": "/Users/sujeethjinesh/Desktop/LatentWire/results/source_private_product_codebook_packet_gate_20260430/remap_107",
      "rotation_sign_accuracy": 0.30859375,
      "scalar_wyner_ziv_accuracy": 0.44921875,
      "target_accuracy": 0.25
    },
    {
      "best_no_source_accuracy": 0.2578125,
      "best_product_codebook_control_accuracy": 0.29296875,
      "budget_bytes": 4,
      "exact_id_parity": true,
      "mean_payload_bytes": 4.0,
      "mean_payload_tokens": 1.0,
      "n": 256,
      "p50_decode_latency_ms": 9.004729508887976,
      "p95_decode_latency_ms": 30.390541011001915,
      "packet_vs_query_aware_oracle_compression": 3.5,
      "product_codebook_accuracy": 0.52734375,
      "product_codebook_controls_ok": true,
      "product_codebook_minus_best_control": 0.234375,
      "product_codebook_minus_best_no_source": 0.26953125,
      "product_codebook_minus_protected": 0.03125,
      "product_codebook_minus_qjl": 0.02734375,
      "product_codebook_minus_scalar": 0.0390625,
      "product_codebook_pass": true,
      "product_codebook_within_002_of_scalar": true,
      "protected_rotated_residual_accuracy": 0.49609375,
      "qjl_residual_accuracy": 0.5,
      "query_aware_text_at_budget_accuracy": 0.25,
      "remap_slot_seed": 107,
      "result_dir": "/Users/sujeethjinesh/Desktop/LatentWire/results/source_private_product_codebook_packet_gate_20260430/remap_107",
      "rotation_sign_accuracy": 0.31640625,
      "scalar_wyner_ziv_accuracy": 0.48828125,
      "target_accuracy": 0.25
    },
    {
      "best_no_source_accuracy": 0.26171875,
      "best_product_codebook_control_accuracy": 0.28125,
      "budget_bytes": 6,
      "exact_id_parity": true,
      "mean_payload_bytes": 6.0,
      "mean_payload_tokens": 1.0,
      "n": 256,
      "p50_decode_latency_ms": 9.759020991623402,
      "p95_decode_latency_ms": 42.16479099704884,
      "packet_vs_query_aware_oracle_compression": 2.3333333333333335,
      "product_codebook_accuracy": 0.5234375,
      "product_codebook_controls_ok": true,
      "product_codebook_minus_best_control": 0.2421875,
      "product_codebook_minus_best_no_source": 0.26171875,
      "product_codebook_minus_protected": 0.03125,
      "product_codebook_minus_qjl": 0.01953125,
      "product_codebook_minus_scalar": 0.00390625,
      "product_codebook_pass": true,
      "product_codebook_within_002_of_scalar": true,
      "protected_rotated_residual_accuracy": 0.4921875,
      "qjl_residual_accuracy": 0.50390625,
      "query_aware_text_at_budget_accuracy": 0.25,
      "remap_slot_seed": 107,
      "result_dir": "/Users/sujeethjinesh/Desktop/LatentWire/results/source_private_product_codebook_packet_gate_20260430/remap_107",
      "rotation_sign_accuracy": 0.33203125,
      "scalar_wyner_ziv_accuracy": 0.51953125,
      "target_accuracy": 0.25
    }
  ],
  "run_dirs": [
    "/Users/sujeethjinesh/Desktop/LatentWire/results/source_private_product_codebook_packet_gate_20260430/remap_101",
    "/Users/sujeethjinesh/Desktop/LatentWire/results/source_private_product_codebook_packet_gate_20260430/remap_103",
    "/Users/sujeethjinesh/Desktop/LatentWire/results/source_private_product_codebook_packet_gate_20260430/remap_107"
  ],
  "systems_latency_pass_gate": false
}